tuberiasjeremy/__init__.py
tuberiasjeremy/matemáticas.py
tuberiasjeremy-0.1.0.dist-info/METADATA
tuberiasjeremy-0.1.0.dist-info/WHEEL
tuberiasjeremy-0.1.0.dist-info/RECORD
