Metadata-Version: 2.1
Name: tuberiasjeremy
Version: 0.1.0
Summary: Paquete de tuberías
Home-page: https://github.com/….
Author: Jeremy Sánchez
Author-email: xjeremy360@gmail.com
Requires-Python: >=3.10.0,<3.12
Classifier: Programming Language :: Python :: 3
Classifier: Programming Language :: Python :: 3.10
Classifier: Programming Language :: Python :: 3.11
Project-URL: Repository, https://github.com/….
Project-URL: repository, https://github.com/…
